mdpax/__init__.py
mdpax/conf/__init__.py
mdpax/core/__init__.py
mdpax/core/problem.py
mdpax/core/solver.py
mdpax/problems/__init__.py
mdpax/problems/forest.py
mdpax/problems/perishable_inventory/de_moor_single_product.py
mdpax/problems/perishable_inventory/hendrix_two_product.py
mdpax/problems/perishable_inventory/mirjalili_platelet.py
mdpax/solvers/__init__.py
mdpax/solvers/periodic_value_iteration.py
mdpax/solvers/policy_iteration.py
mdpax/solvers/relative_value_iteration.py
mdpax/solvers/semi_async_value_iteration.py
mdpax/solvers/value_iteration.py
mdpax/utils/__init__.py
mdpax/utils/batch_processing.py
mdpax/utils/checkpointing.py
mdpax/utils/logging.py
mdpax/utils/spaces.py
mdpax/utils/types.py
mdpax-0.2.1.dist-info/METADATA
mdpax-0.2.1.dist-info/WHEEL
mdpax-0.2.1.dist-info/licenses/LICENSE
mdpax-0.2.1.dist-info/RECORD
