Metadata-Version: 2.4
Name: mdpax
Version: 0.2.1
Summary: GPU-accelerated MDP solvers in Python with JAX
Author-email: Joe Farrington <farrington.joe@gmail.com>
License: MIT
License-File: LICENSE
Classifier: Development Status :: 4 - Beta
Classifier: Intended Audience :: Science/Research
Classifier: License :: OSI Approved :: MIT License
Classifier: Programming Language :: Python :: 3
Classifier: Programming Language :: Python :: 3.10
Classifier: Topic :: Scientific/Engineering
Requires-Python: >=3.10
Requires-Dist: chex>=0.1.88
Requires-Dist: hydra-core>=1.3.2
Requires-Dist: jax>=0.4.30; sys_platform != 'linux'
Requires-Dist: jax[cuda12]>=0.4.30; sys_platform == 'linux'
Requires-Dist: jaxtyping>=0.2.36
Requires-Dist: loguru>=0.7.3
Requires-Dist: numpy>=1.26.0
Requires-Dist: numpyro>=0.16.1
Requires-Dist: orbax>=0.1.9
Provides-Extra: docs
Requires-Dist: ipython>=8.18.1; extra == 'docs'
Requires-Dist: myst-parser>=4.0.0; extra == 'docs'
Requires-Dist: nbsphinx>=0.9.6; extra == 'docs'
Requires-Dist: sphinx-rtd-theme>=3.0.2; extra == 'docs'
Requires-Dist: sphinx>=7.4.7; extra == 'docs'
Provides-Extra: examples
Requires-Dist: jupyter>=1.1.1; extra == 'examples'
Requires-Dist: matplotlib>=3.9.4; extra == 'examples'
Requires-Dist: pymdptoolbox>=4.0b3; extra == 'examples'
Provides-Extra: examples-colab
Requires-Dist: orbax-checkpoint==0.11.23; extra == 'examples-colab'
Requires-Dist: pymdptoolbox>=4.0b3; extra == 'examples-colab'
